miniogre/__init__.py
miniogre/actions.py
miniogre/config.py
miniogre/constants.py
miniogre/encodings/9b5ad71b2ce5302211f9c61530b329a4922fc6a4
miniogre/main.py
miniogre-0.12.0.dist-info/LICENSE
miniogre-0.12.0.dist-info/METADATA
miniogre-0.12.0.dist-info/WHEEL
miniogre-0.12.0.dist-info/entry_points.txt
miniogre-0.12.0.dist-info/RECORD
