Metadata-Version: 2.3
Name: miniogre
Version: 0.12.0
Summary: miniogre: from source code to reproducible environment, in seconds.
Home-page: https://github.com/ogre-run/miniogre
Author: Wilder Lopes
Author-email: wilder@ogre.run
Requires-Python: >=3.10,<4.0
Classifier: Programming Language :: Python :: 3
Classifier: Programming Language :: Python :: 3.10
Classifier: Programming Language :: Python :: 3.11
Classifier: Programming Language :: Python :: 3.12
Classifier: Programming Language :: Python :: 3.13
Requires-Dist: autopep8 (>=2.0.4,<3.0.0)
Requires-Dist: cyclonedx-py (>=1.0.1,<2.0.0)
Requires-Dist: docker (>=5.0.0,<6.0.0)
Requires-Dist: emoji (>=2.10.1,<3.0.0)
Requires-Dist: google-generativeai (==0.5.2)
Requires-Dist: gptify (>=0.3.4,<0.4.0)
Requires-Dist: groq (==0.5.0)
Requires-Dist: mistralai (>=0.1.3,<0.2.0)
Requires-Dist: octoai-sdk (>=0.9.0,<0.10.0)
Requires-Dist: openai (==1.21.2)
Requires-Dist: pip-licenses (>=4.3.4,<5.0.0)
Requires-Dist: pyfiglet (>=1.0.2,<2.0.0)
Requires-Dist: python-dotenv (>=0.19.0,<0.20.0)
Requires-Dist: rich (>=13.7.0,<14.0.0)
Requires-Dist: tiktoken (==0.6.0)
Requires-Dist: typer (==0.9.0)
Requires-Dist: tzlocal (>=5.2,<6.0)
Requires-Dist: uv (>=0.5.7,<0.6.0)
Requires-Dist: yaspin (>=3.0.1,<4.0.0)
